odoo/addons/pos_to_weight_by_product_uom/README.rst
odoo/addons/pos_to_weight_by_product_uom/__init__.py
odoo/addons/pos_to_weight_by_product_uom/__manifest__.py
odoo/addons/pos_to_weight_by_product_uom/demo/res_groups.xml
odoo/addons/pos_to_weight_by_product_uom/demo/uom_category.xml
odoo/addons/pos_to_weight_by_product_uom/demo/uom_uom.xml
odoo/addons/pos_to_weight_by_product_uom/i18n/ca.po
odoo/addons/pos_to_weight_by_product_uom/i18n/de.po
odoo/addons/pos_to_weight_by_product_uom/i18n/es.po
odoo/addons/pos_to_weight_by_product_uom/i18n/es_MX.po
odoo/addons/pos_to_weight_by_product_uom/i18n/fi.po
odoo/addons/pos_to_weight_by_product_uom/i18n/fr.po
odoo/addons/pos_to_weight_by_product_uom/i18n/fr_CH.po
odoo/addons/pos_to_weight_by_product_uom/i18n/hr.po
odoo/addons/pos_to_weight_by_product_uom/i18n/hr_HR.po
odoo/addons/pos_to_weight_by_product_uom/i18n/it.po
odoo/addons/pos_to_weight_by_product_uom/i18n/pos_to_weight_by_product_uom.pot
odoo/addons/pos_to_weight_by_product_uom/i18n/pt.po
odoo/addons/pos_to_weight_by_product_uom/i18n/pt_BR.po
odoo/addons/pos_to_weight_by_product_uom/i18n/ro.po
odoo/addons/pos_to_weight_by_product_uom/i18n/sl.po
odoo/addons/pos_to_weight_by_product_uom/i18n/tr_TR.po
odoo/addons/pos_to_weight_by_product_uom/i18n/vi_VN.po
odoo/addons/pos_to_weight_by_product_uom/i18n/zh_CN.po
odoo/addons/pos_to_weight_by_product_uom/models/__init__.py
odoo/addons/pos_to_weight_by_product_uom/models/product_product.py
odoo/addons/pos_to_weight_by_product_uom/models/product_template.py
odoo/addons/pos_to_weight_by_product_uom/models/uom_category.py
odoo/addons/pos_to_weight_by_product_uom/models/uom_uom.py
odoo/addons/pos_to_weight_by_product_uom/readme/CONFIGURE.rst
odoo/addons/pos_to_weight_by_product_uom/readme/CONTRIBUTORS.rst
odoo/addons/pos_to_weight_by_product_uom/readme/DESCRIPTION.rst
odoo/addons/pos_to_weight_by_product_uom/readme/USAGE.rst
odoo/addons/pos_to_weight_by_product_uom/static/description/icon.png
odoo12_addon_pos_to_weight_by_product_uom-12.0.1.0.1.dist-info/METADATA
odoo12_addon_pos_to_weight_by_product_uom-12.0.1.0.1.dist-info/WHEEL
odoo12_addon_pos_to_weight_by_product_uom-12.0.1.0.1.dist-info/top_level.txt
odoo12_addon_pos_to_weight_by_product_uom-12.0.1.0.1.dist-info/RECORD
